azblobexplorer/__init__.py
azblobexplorer/base.py
azblobexplorer/cli.py
azblobexplorer/delete.py
azblobexplorer/download.py
azblobexplorer/exceptions.py
azblobexplorer/upload.py
azblobexplorer-2.0.dist-info/LICENSE
azblobexplorer-2.0.dist-info/METADATA
azblobexplorer-2.0.dist-info/WHEEL
azblobexplorer-2.0.dist-info/top_level.txt
azblobexplorer-2.0.dist-info/RECORD
